[
  {
    "id": "3a388d35eddd",
    "title": "Mexico 1-0 South Africa - Julián Quiñones 9'",
    "url": "https://www.reddit.com/r/soccer/comments/1u38ii8/mexico_10_south_africa_juli%C3%A1n_qui%C3%B1ones_9",
    "canonicalUrl": "https://www.reddit.com/r/soccer/comments/1u38ii8/mexico_10_south_africa_juli%C3%A1n_qui%C3%B1ones_9/",
    "source": "Reddit",
    "sourceDetail": "r/soccer",
    "description": "Posted in r/soccer by u/977x • 7,618 points and 697 comments",
    "thumbnailRemoteUrl": "https://www.redditstatic.com/new-icon.png",
    "thumbnailLocalPath": "assets/thumbs/3a388d35eddd.png",
    "externalUrl": null,
    "archivedUrl": "https://web.archive.org/web/20260611205954/https://www.reddit.com/r/soccer/comments/1u38ii8/mexico_10_south_africa_juli%C3%A1n_qui%C3%B1ones_9/",
    "postDate": "2026-06-11T19:14:47Z",
    "dateSaved": "2026-06-14T12:41:57Z",
    "matchId": "MEX-RSA-2026-06-11",
    "matchLabel": "🇲🇽 Mexico vs 🇿🇦 South Africa",
    "stage": "Group stage",
    "group": "A",
    "teams": [
      "Mexico",
      "South Africa"
    ],
    "teamCodes": [
      "MEX",
      "RSA"
    ],
    "scoreLabel": "🇲🇽 Mexico 2–0 🇿🇦 South Africa",
    "goals": [
      {
        "team": "Mexico",
        "player": "Julián Quiñones",
        "minute": 9,
        "ownGoal": false,
        "penalty": false
      },
      {
        "team": "Mexico",
        "player": "Raúl Jiménez",
        "minute": 67,
        "ownGoal": false,
        "penalty": false
      }
    ],
    "candidateMatches": [],
    "type": [],
    "tags": [
      "Goal",
      "Highlights"
    ],
    "importance": null,
    "note": "",
    "backup": "",
    "metadataConfidence": {
      "match": 1,
      "teams": 1,
      "stage": 1,
      "score": 1
    },
    "needsReview": false
  },
  {
    "id": "453529037564",
    "title": "Mexico [2] - 0 South Africa - Raúl Jiménez 67'",
    "url": "https://www.reddit.com/r/soccer/comments/1u3anmt/mexico_2_0_south_africa_ra%C3%BAl_jim%C3%A9nez_67",
    "canonicalUrl": "https://www.reddit.com/r/soccer/comments/1u3anmt/mexico_2_0_south_africa_ra%C3%BAl_jim%C3%A9nez_67/",
    "source": "Reddit",
    "sourceDetail": "r/soccer",
    "description": "Posted in r/soccer by u/gbogaz • 3,972 points and 288 comments",
    "thumbnailRemoteUrl": "https://external-preview.redd.it/HF4A2IckCT9m7oJM2lQZ31APpSyTyQc5-v5pXmaG3e0.jpeg?width=140&height=78&auto=webp",
    "thumbnailLocalPath": null,
    "externalUrl": null,
    "archivedUrl": null,
    "postDate": "2026-06-11T20:34:42Z",
    "dateSaved": "2026-06-14T13:16:46Z",
    "matchId": "MEX-RSA-2026-06-11",
    "matchLabel": "🇲🇽 Mexico vs 🇿🇦 South Africa",
    "stage": "Group stage",
    "group": "A",
    "teams": [
      "Mexico",
      "South Africa"
    ],
    "teamCodes": [
      "MEX",
      "RSA"
    ],
    "scoreLabel": "🇲🇽 Mexico 2–0 🇿🇦 South Africa",
    "goals": [
      {
        "team": "Mexico",
        "player": "Julián Quiñones",
        "minute": 9,
        "ownGoal": false,
        "penalty": false
      },
      {
        "team": "Mexico",
        "player": "Raúl Jiménez",
        "minute": 67,
        "ownGoal": false,
        "penalty": false
      }
    ],
    "candidateMatches": [],
    "type": [],
    "tags": [
      "Goal",
      "Highlights"
    ],
    "importance": null,
    "note": "",
    "backup": "",
    "metadataConfidence": {
      "match": 1,
      "teams": 1,
      "stage": 1,
      "score": 1
    },
    "needsReview": false
  },
  {
    "id": "4d3ddb0cd56f",
    "title": "South Korea [2]-1 Czechia - Hyeon-gyu Oh 80'",
    "url": "https://www.reddit.com/r/soccer/comments/1u3k7m5/south_korea_21_czechia_hyeongyu_oh_80",
    "canonicalUrl": "https://www.reddit.com/r/soccer/comments/1u3k7m5/south_korea_21_czechia_hyeongyu_oh_80/",
    "source": "Reddit",
    "sourceDetail": "r/soccer",
    "description": "Posted in r/soccer by u/977x • 1,810 points and 192 comments",
    "thumbnailRemoteUrl": "https://www.redditstatic.com/new-icon.png",
    "thumbnailLocalPath": "assets/thumbs/4d3ddb0cd56f.png",
    "externalUrl": null,
    "archivedUrl": "https://web.archive.org/web/20260612035001/https://www.reddit.com/r/soccer/comments/1u3k7m5/south_korea_21_czechia_hyeongyu_oh_80/",
    "postDate": "2026-06-12T03:38:40Z",
    "dateSaved": "2026-06-14T13:16:49Z",
    "matchId": "KOR-CZE-2026-06-11",
    "matchLabel": "🇰🇷 South Korea vs 🇨🇿 Czech Republic",
    "stage": "Group stage",
    "group": "A",
    "teams": [
      "South Korea",
      "Czech Republic"
    ],
    "teamCodes": [
      "KOR",
      "CZE"
    ],
    "scoreLabel": "🇰🇷 South Korea 2–1 🇨🇿 Czech Republic",
    "goals": [
      {
        "team": "South Korea",
        "player": "Hwang In-Beom",
        "minute": 67,
        "ownGoal": false,
        "penalty": false
      },
      {
        "team": "South Korea",
        "player": "Oh Hyeon-Gyu",
        "minute": 80,
        "ownGoal": false,
        "penalty": false
      },
      {
        "team": "Czech Republic",
        "player": "Ladislav Krejcí",
        "minute": 59,
        "ownGoal": false,
        "penalty": false
      }
    ],
    "candidateMatches": [],
    "type": [],
    "tags": [
      "Goal",
      "Highlights"
    ],
    "importance": null,
    "note": "",
    "backup": "",
    "metadataConfidence": {
      "match": 1,
      "teams": 1,
      "stage": 1,
      "score": 1
    },
    "needsReview": false
  },
  {
    "id": "ebeef2e28713",
    "title": "South Korea [1]-1 Czechia - Hwang In-beom 67'",
    "url": "https://www.reddit.com/r/soccer/comments/1u3k0hx/south_korea_11_czechia_hwang_inbeom_67",
    "canonicalUrl": "https://www.reddit.com/r/soccer/comments/1u3k0hx/south_korea_11_czechia_hwang_inbeom_67/",
    "source": "Reddit",
    "sourceDetail": "r/soccer",
    "description": "Posted in r/soccer by u/977x • 4,776 points and 327 comments",
    "thumbnailRemoteUrl": "https://external-preview.redd.it/uINJZJPlh6jHu5mYJGjBaUOXfl7_IGYjmgmKBWdcIRc.jpeg?width=140&height=78&auto=webp",
    "thumbnailLocalPath": null,
    "externalUrl": null,
    "archivedUrl": "https://web.archive.org/web/20260612034734/https://www.reddit.com/r/soccer/comments/1u3k0hx/south_korea_11_czechia_hwang_inbeom_67/",
    "postDate": "2026-06-12T03:28:30Z",
    "dateSaved": "2026-06-14T13:16:57Z",
    "matchId": "KOR-CZE-2026-06-11",
    "matchLabel": "🇰🇷 South Korea vs 🇨🇿 Czech Republic",
    "stage": "Group stage",
    "group": "A",
    "teams": [
      "South Korea",
      "Czech Republic"
    ],
    "teamCodes": [
      "KOR",
      "CZE"
    ],
    "scoreLabel": "🇰🇷 South Korea 2–1 🇨🇿 Czech Republic",
    "goals": [
      {
        "team": "South Korea",
        "player": "Hwang In-Beom",
        "minute": 67,
        "ownGoal": false,
        "penalty": false
      },
      {
        "team": "South Korea",
        "player": "Oh Hyeon-Gyu",
        "minute": 80,
        "ownGoal": false,
        "penalty": false
      },
      {
        "team": "Czech Republic",
        "player": "Ladislav Krejcí",
        "minute": 59,
        "ownGoal": false,
        "penalty": false
      }
    ],
    "candidateMatches": [],
    "type": [],
    "tags": [
      "Goal",
      "Highlights"
    ],
    "importance": null,
    "note": "",
    "backup": "",
    "metadataConfidence": {
      "match": 1,
      "teams": 1,
      "stage": 1,
      "score": 1
    },
    "needsReview": false
  },
  {
    "id": "73a1da7885aa",
    "title": "Mexican fans spot a South Korean fan and immediately adopt him",
    "url": "https://www.reddit.com/r/soccer/comments/1u3cj9p/mexican_fans_spot_a_south_korean_fan_and",
    "canonicalUrl": "https://www.reddit.com/r/soccer/comments/1u3cj9p/mexican_fans_spot_a_south_korean_fan_and/",
    "source": "Reddit",
    "sourceDetail": "r/soccer",
    "description": "Posted in r/soccer by u/Heisenberg1_007 • 34,806 points and 844 comments",
    "thumbnailRemoteUrl": "https://external-preview.redd.it/NnpreHM4cjA1cTZoMa6iSPx5WRAYHwM-VUA52etYAAlnGAH3uInTf0ouhHol.png?width=140&height=140&crop=1:1,smart&format=jpg&auto=webp",
    "thumbnailLocalPath": null,
    "externalUrl": null,
    "archivedUrl": "https://web.archive.org/web/20260612000041/https://www.reddit.com/r/soccer/comments/1u3cj9p/mexican_fans_spot_a_south_korean_fan_and/",
    "postDate": "2026-06-11T21:47:19Z",
    "dateSaved": "2026-06-14T13:17:02Z",
    "matchId": null,
    "matchLabel": null,
    "stage": null,
    "group": null,
    "teams": [],
    "teamCodes": [],
    "scoreLabel": null,
    "goals": [],
    "candidateMatches": [],
    "type": [],
    "tags": [
      "Vibes"
    ],
    "importance": null,
    "note": "",
    "backup": "",
    "metadataConfidence": {
      "match": 0,
      "teams": 0,
      "stage": 0,
      "score": 0
    },
    "needsReview": false
  },
  {
    "id": "e054f8781450",
    "title": "The South Korean fans couldn't bring the tequila bottle inside the stadium, so they started drinking it all together outside and also invited the Mexican fans to join them.",
    "url": "https://www.reddit.com/r/soccer/comments/1u3lcpy/the_south_korean_fans_couldnt_bring_the_tequila",
    "canonicalUrl": "https://www.reddit.com/r/soccer/comments/1u3lcpy/the_south_korean_fans_couldnt_bring_the_tequila/",
    "source": "Reddit",
    "sourceDetail": "r/soccer",
    "description": "Posted in r/soccer by u/OptimusCloyster • 11,216 points and 315 comments",
    "thumbnailRemoteUrl": "https://external-preview.redd.it/bTBhODJmMDc2czZoMXwBxXZz0N6-KHkVAAqDjwhl113zCjTazFJH5s-Lg5JM.png?width=140&height=140&crop=1:1,smart&format=jpg&auto=webp",
    "thumbnailLocalPath": null,
    "externalUrl": null,
    "archivedUrl": "https://web.archive.org/web/20260612051616/https://www.reddit.com/r/soccer/comments/1u3lcpy/the_south_korean_fans_couldnt_bring_the_tequila/",
    "postDate": "2026-06-12T04:37:33Z",
    "dateSaved": "2026-06-14T13:17:10Z",
    "matchId": null,
    "matchLabel": null,
    "stage": null,
    "group": null,
    "teams": [],
    "teamCodes": [],
    "scoreLabel": null,
    "goals": [],
    "candidateMatches": [],
    "type": [],
    "tags": [
      "Vibes"
    ],
    "importance": null,
    "note": "",
    "backup": "",
    "metadataConfidence": {
      "match": 0,
      "teams": 0,
      "stage": 0,
      "score": 0
    },
    "needsReview": false
  },
  {
    "id": "bdaad844883c",
    "title": "[WC2026 Matchday 1] All Goals with Scoring Nation Commentary",
    "url": "https://www.reddit.com/r/soccer/comments/1u3s7ai/wc2026_matchday_1_all_goals_with_scoring_nation",
    "canonicalUrl": "https://www.reddit.com/r/soccer/comments/1u3s7ai/wc2026_matchday_1_all_goals_with_scoring_nation/",
    "source": "Reddit",
    "sourceDetail": "r/soccer",
    "description": "Posted in r/soccer by u/HOPSCROTCH • 10,136 points and 314 comments",
    "thumbnailRemoteUrl": "https://external-preview.redd.it/aHNpd2kzNnAzdTZoMfAvVGiF6GO80B2GHZTCsElKoP64awxY0A3VJMxEo6fi.png?width=140&height=78&format=jpg&auto=webp",
    "thumbnailLocalPath": null,
    "externalUrl": null,
    "archivedUrl": null,
    "postDate": "2026-06-12T11:07:00Z",
    "dateSaved": "2026-06-15T11:17:04Z",
    "matchId": null,
    "matchLabel": null,
    "stage": null,
    "group": null,
    "teams": [],
    "teamCodes": [],
    "scoreLabel": null,
    "goals": [],
    "candidateMatches": [],
    "type": [],
    "tags": [
      "Highlights"
    ],
    "pinnedTags": [],
    "importance": null,
    "note": "",
    "backup": "",
    "metadataConfidence": {
      "match": 0,
      "teams": 0,
      "stage": 0,
      "score": 0
    },
    "needsReview": false,
    "matchLocked": false
  },
  {
    "id": "e76bc76b5a71",
    "title": "Bosnian fans in Toronto before their game against Canada today",
    "url": "https://www.reddit.com/r/soccer/comments/1u3zcck/bosnian_fans_in_toronto_before_their_game_against",
    "canonicalUrl": "https://www.reddit.com/r/soccer/comments/1u3zcck/bosnian_fans_in_toronto_before_their_game_against/",
    "source": "Reddit",
    "sourceDetail": "r/soccer",
    "description": "Posted in r/soccer by u/ujpanak • 4,953 points and 430 comments",
    "thumbnailRemoteUrl": "https://external-preview.redd.it/ZDVwN2ZhOXBqdjZoMbzbzFhpboAW1P9K4kWyN7nlhZDGlE82OjnTQeG2cHXZ.png?width=140&height=140&crop=1:1,smart&format=jpg&auto=webp",
    "thumbnailLocalPath": null,
    "externalUrl": null,
    "archivedUrl": null,
    "postDate": "2026-06-12T15:58:36Z",
    "dateSaved": "2026-06-15T11:17:44Z",
    "matchId": "CAN-BIH-2026-06-12",
    "matchLabel": "🇨🇦 Canada vs 🇧🇦 Bosnia & Herzegovina",
    "stage": "Group stage",
    "group": "B",
    "teams": [
      "Canada",
      "Bosnia & Herzegovina"
    ],
    "teamCodes": [
      "CAN",
      "BIH"
    ],
    "scoreLabel": "🇨🇦 Canada 1–1 🇧🇦 Bosnia & Herzegovina",
    "goals": [
      {
        "team": "Canada",
        "player": "Cyle Larin",
        "minute": 78,
        "ownGoal": false,
        "penalty": false
      },
      {
        "team": "Bosnia & Herzegovina",
        "player": "Jovo Lukić",
        "minute": 21,
        "ownGoal": false,
        "penalty": false
      }
    ],
    "candidateMatches": [],
    "type": [],
    "tags": [
      "Vibes"
    ],
    "pinnedTags": [],
    "importance": null,
    "note": "",
    "backup": "",
    "metadataConfidence": {
      "match": 1,
      "teams": 1,
      "stage": 1,
      "score": 1
    },
    "needsReview": false,
    "matchLocked": false
  },
  {
    "id": "91c1b6e6379c",
    "title": "South Korean High school students' reaction to the second goal while watching it live from their classroom",
    "url": "https://www.reddit.com/r/soccer/comments/1u3x4sv/south_korean_high_school_students_reaction_to_the",
    "canonicalUrl": "https://www.reddit.com/r/soccer/comments/1u3x4sv/south_korean_high_school_students_reaction_to_the/",
    "source": "Reddit",
    "sourceDetail": "r/soccer",
    "description": "Posted in r/soccer by u/achilles-_-23 • 8,425 points and 177 comments",
    "thumbnailRemoteUrl": "https://external-preview.redd.it/dmU2d2I2emU1djZoMa9p4aswa9IrGtyxF4vkWz_qgRE1sy82HcYm2QawVbgF.png?width=140&height=140&crop=1:1,smart&format=jpg&auto=webp",
    "thumbnailLocalPath": null,
    "externalUrl": null,
    "archivedUrl": "https://web.archive.org/web/20260612194758/https://www.reddit.com/r/soccer/comments/1u3x4sv/south_korean_high_school_students_reaction_to_the/",
    "postDate": "2026-06-12T14:38:27Z",
    "dateSaved": "2026-06-15T11:17:49Z",
    "matchId": null,
    "matchLabel": null,
    "stage": null,
    "group": null,
    "teams": [],
    "teamCodes": [],
    "scoreLabel": null,
    "goals": [],
    "candidateMatches": [],
    "type": [],
    "tags": [
      "Vibes"
    ],
    "pinnedTags": [],
    "importance": null,
    "note": "",
    "backup": "",
    "metadataConfidence": {
      "match": 0,
      "teams": 0,
      "stage": 0,
      "score": 0
    },
    "needsReview": false
  },
  {
    "id": "01bd7fd26e58",
    "title": "Canadian fans before the match against Bosnia today",
    "url": "https://www.reddit.com/r/soccer/comments/1u40a7d/canadian_fans_before_the_match_against_bosnia",
    "canonicalUrl": "https://www.reddit.com/r/soccer/comments/1u40a7d/canadian_fans_before_the_match_against_bosnia/",
    "source": "Reddit",
    "sourceDetail": "r/soccer",
    "description": "Posted in r/soccer by u/Prestigious-Back-981 • 6,026 points and 278 comments",
    "thumbnailRemoteUrl": "https://external-preview.redd.it/Ym15eWQ5MGpwdjZoMZuIhlP1g0uTT-QnKqHFy9QNwiAdzjg_Oy5Z6RRmjRJs.png?width=140&height=78&format=jpg&auto=webp",
    "thumbnailLocalPath": null,
    "externalUrl": null,
    "archivedUrl": null,
    "postDate": "2026-06-12T16:31:11Z",
    "dateSaved": "2026-06-15T11:18:32Z",
    "matchId": "CAN-BIH-2026-06-12",
    "matchLabel": "🇨🇦 Canada vs 🇧🇦 Bosnia & Herzegovina",
    "stage": "Group stage",
    "group": "B",
    "teams": [
      "Canada",
      "Bosnia & Herzegovina"
    ],
    "teamCodes": [
      "CAN",
      "BIH"
    ],
    "scoreLabel": "🇨🇦 Canada 1–1 🇧🇦 Bosnia & Herzegovina",
    "goals": [
      {
        "team": "Canada",
        "player": "Cyle Larin",
        "minute": 78,
        "ownGoal": false,
        "penalty": false
      },
      {
        "team": "Bosnia & Herzegovina",
        "player": "Jovo Lukić",
        "minute": 21,
        "ownGoal": false,
        "penalty": false
      }
    ],
    "candidateMatches": [],
    "type": [],
    "tags": [
      "Vibes"
    ],
    "pinnedTags": [],
    "importance": null,
    "note": "",
    "backup": "",
    "metadataConfidence": {
      "match": 1,
      "teams": 1,
      "stage": 1,
      "score": 1
    },
    "needsReview": false,
    "matchLocked": false
  },
  {
    "id": "678901a4afdf",
    "title": "Mexicans dancing and singing GANGNAM STYLE with the Koreans in Mexico after South Korea's victory in the World Cup",
    "url": "https://www.reddit.com/r/soccer/comments/1u414gk/mexicans_dancing_and_singing_gangnam_style_with",
    "canonicalUrl": "https://www.reddit.com/r/soccer/comments/1u414gk/mexicans_dancing_and_singing_gangnam_style_with/",
    "source": "Reddit",
    "sourceDetail": "r/soccer",
    "description": "Posted in r/soccer by u/BurgerNugget12 • 5,850 points and 178 comments",
    "thumbnailRemoteUrl": "https://external-preview.redd.it/d2x1Mm4ydHF1djZoMVaIHja8_gJI7AT_RA-SkqpLxOFSqQUMefGg_q9GDLZs.png?width=140&height=140&crop=1:1,smart&format=jpg&auto=webp",
    "thumbnailLocalPath": null,
    "externalUrl": null,
    "archivedUrl": null,
    "postDate": "2026-06-12T17:01:30Z",
    "dateSaved": "2026-06-15T11:19:16Z",
    "matchId": null,
    "matchLabel": null,
    "stage": null,
    "group": null,
    "teams": [],
    "teamCodes": [],
    "scoreLabel": null,
    "goals": [],
    "candidateMatches": [],
    "matchLocked": true,
    "type": [],
    "tags": [
      "Vibes"
    ],
    "pinnedTags": [],
    "importance": null,
    "note": "",
    "backup": "",
    "metadataConfidence": {
      "match": 0,
      "teams": 0,
      "stage": 0,
      "score": 0
    },
    "needsReview": false
  },
  {
    "id": "5842ba2765d8",
    "title": "Alternate angles of Sead Kolasinac's goal line clearance against Canada",
    "url": "https://www.reddit.com/r/soccer/comments/1u46f6b/alternate_angles_of_sead_kolasinacs_goal_line",
    "canonicalUrl": "https://www.reddit.com/r/soccer/comments/1u46f6b/alternate_angles_of_sead_kolasinacs_goal_line/",
    "source": "Reddit",
    "sourceDetail": "r/soccer",
    "description": "Posted in r/soccer by u/977x • 9,196 points and 215 comments",
    "thumbnailRemoteUrl": "https://external-preview.redd.it/ZTFyaXhzNTJ1dzZoMSnUoBn7Eo2vhBzubNTPkBs37ftXp8S_agW1hMcG1DSx.png?width=140&height=78&format=jpg&auto=webp",
    "thumbnailLocalPath": null,
    "externalUrl": null,
    "archivedUrl": "https://web.archive.org/web/20260613014717/https://www.reddit.com/r/soccer/comments/1u46f6b/alternate_angles_of_sead_kolasinacs_goal_line/",
    "postDate": "2026-06-12T20:18:20Z",
    "dateSaved": "2026-06-15T11:19:19Z",
    "matchId": "CAN-BIH-2026-06-12",
    "matchLabel": "🇨🇦 Canada vs 🇧🇦 Bosnia & Herzegovina",
    "stage": "Group stage",
    "group": "B",
    "teams": [
      "Canada",
      "Bosnia & Herzegovina"
    ],
    "teamCodes": [
      "CAN",
      "BIH"
    ],
    "scoreLabel": "🇨🇦 Canada 1–1 🇧🇦 Bosnia & Herzegovina",
    "goals": [
      {
        "team": "Canada",
        "player": "Cyle Larin",
        "minute": 78,
        "ownGoal": false,
        "penalty": false
      },
      {
        "team": "Bosnia & Herzegovina",
        "player": "Jovo Lukić",
        "minute": 21,
        "ownGoal": false,
        "penalty": false
      }
    ],
    "candidateMatches": [],
    "type": [],
    "tags": [
      "Highlights"
    ],
    "pinnedTags": [],
    "importance": null,
    "note": "",
    "backup": "",
    "metadataConfidence": {
      "match": 1,
      "teams": 1,
      "stage": 1,
      "score": 1
    },
    "needsReview": false,
    "matchLocked": false
  },
  {
    "id": "90f4d2d2d51a",
    "title": "A duck in Mexico wearing a Mexican jersey",
    "url": "https://www.reddit.com/r/soccer/comments/1u3vppf/a_duck_in_mexico_wearing_a_mexican_jersey",
    "canonicalUrl": "https://www.reddit.com/r/soccer/comments/1u3vppf/a_duck_in_mexico_wearing_a_mexican_jersey/",
    "source": "Reddit",
    "sourceDetail": "r/soccer",
    "description": "Posted in r/soccer by u/AgeNovel3566 • 29,622 points and 342 comments",
    "thumbnailRemoteUrl": "https://external-preview.redd.it/NzJhZzdmeHd2dTZoMTqGCKQ7Q-u0q95R-1T-_HyVENT7Pw6wHtIsYe2dkewf.png?width=140&height=140&crop=1:1,smart&format=jpg&auto=webp",
    "thumbnailLocalPath": null,
    "externalUrl": null,
    "archivedUrl": null,
    "postDate": "2026-06-12T13:45:12Z",
    "dateSaved": "2026-06-15T11:20:40Z",
    "matchId": null,
    "matchLabel": null,
    "stage": null,
    "group": null,
    "teams": [],
    "teamCodes": [],
    "scoreLabel": null,
    "goals": [],
    "candidateMatches": [],
    "type": [],
    "tags": [
      "Vibes"
    ],
    "pinnedTags": [
      "Vibes"
    ],
    "importance": null,
    "note": "",
    "backup": "",
    "metadataConfidence": {
      "match": 0,
      "teams": 0,
      "stage": 0,
      "score": 0
    },
    "needsReview": true,
    "matchLocked": false
  },
  {
    "id": "860b733a9f0e",
    "title": "USA 3-0 Paraguay - Folarin Balogun 45+5'",
    "url": "https://www.reddit.com/r/soccer/comments/1u4e3qu/usa_30_paraguay_folarin_balogun_455",
    "canonicalUrl": "https://www.reddit.com/r/soccer/comments/1u4e3qu/usa_30_paraguay_folarin_balogun_455/",
    "source": "Reddit",
    "sourceDetail": "r/soccer",
    "description": "Posted in r/soccer by u/977x • 7,029 points and 1,074 comments",
    "thumbnailRemoteUrl": "https://www.redditstatic.com/new-icon.png",
    "thumbnailLocalPath": "assets/thumbs/860b733a9f0e.png",
    "externalUrl": null,
    "archivedUrl": null,
    "postDate": "2026-06-13T01:51:33Z",
    "dateSaved": "2026-06-15T11:21:30Z",
    "matchId": "USA-PAR-2026-06-12",
    "matchLabel": "🇺🇸 USA vs 🇵🇾 Paraguay",
    "stage": "Group stage",
    "group": "D",
    "teams": [
      "USA",
      "Paraguay"
    ],
    "teamCodes": [
      "USA",
      "PAR"
    ],
    "scoreLabel": "🇺🇸 USA 4–1 🇵🇾 Paraguay",
    "goals": [
      {
        "team": "USA",
        "player": "Damian Bobadilla",
        "minute": 7,
        "ownGoal": true,
        "penalty": false
      },
      {
        "team": "USA",
        "player": "Folarin Balogun",
        "minute": 31,
        "ownGoal": false,
        "penalty": false
      },
      {
        "team": "USA",
        "player": "Folarin Balogun",
        "minute": 45,
        "ownGoal": false,
        "penalty": false
      },
      {
        "team": "USA",
        "player": "Giovanni Reyna",
        "minute": 90,
        "ownGoal": false,
        "penalty": false
      },
      {
        "team": "Paraguay",
        "player": "Mauricio",
        "minute": 73,
        "ownGoal": false,
        "penalty": false
      }
    ],
    "candidateMatches": [],
    "type": [],
    "tags": [
      "Goal",
      "Highlights",
      "Banger"
    ],
    "pinnedTags": [
      "Banger"
    ],
    "importance": null,
    "note": "",
    "backup": "",
    "metadataConfidence": {
      "match": 1,
      "teams": 1,
      "stage": 1,
      "score": 1
    },
    "needsReview": false
  },
  {
    "id": "8be8ba299c2e",
    "title": "Alternate angle of Balogun's goal against Paraguay 45+5'",
    "url": "https://www.reddit.com/r/soccer/comments/1u4ed4q/alternate_angle_of_baloguns_goal_against_paraguay",
    "canonicalUrl": "https://www.reddit.com/r/soccer/comments/1u4ed4q",
    "source": "Reddit",
    "sourceDetail": "r/soccer",
    "description": null,
    "thumbnailRemoteUrl": "data:image/svg+xml;utf8,%3Csvg%20xmlns%3D%22http%3A%2F%2Fwww.w3.org%2F2000%2Fsvg%22%20width%3D%22120%22%20height%3D%22120%22%20viewBox%3D%220%200%20120%20120%22%3E%3Crect%20width%3D%22120%22%20height%3D%22120%22%20rx%3D%2216%22%20fill%3D%22%23ff4500%22%2F%3E%3Ccircle%20cx%3D%2260%22%20cy%3D%2266%22%20r%3D%2234%22%20fill%3D%22%23fff%22%2F%3E%3Ccircle%20cx%3D%2246%22%20cy%3D%2264%22%20r%3D%226%22%20fill%3D%22%23ff4500%22%2F%3E%3Ccircle%20cx%3D%2274%22%20cy%3D%2264%22%20r%3D%226%22%20fill%3D%22%23ff4500%22%2F%3E%3Cpath%20d%3D%22M44%2080%20q16%2012%2032%200%22%20stroke%3D%22%23ff4500%22%20stroke-width%3D%225%22%20fill%3D%22none%22%20stroke-linecap%3D%22round%22%2F%3E%3C%2Fsvg%3E",
    "thumbnailLocalPath": null,
    "externalUrl": null,
    "archivedUrl": null,
    "postDate": null,
    "dateSaved": "2026-06-15T12:45:04Z",
    "matchId": "USA-PAR-2026-06-12",
    "matchLabel": "🇺🇸 USA vs 🇵🇾 Paraguay",
    "stage": "Group stage",
    "group": "D",
    "teams": [
      "USA",
      "Paraguay"
    ],
    "teamCodes": [
      "USA",
      "PAR"
    ],
    "scoreLabel": "🇺🇸 USA 4–1 🇵🇾 Paraguay",
    "goals": [
      {
        "team": "USA",
        "player": "Damian Bobadilla",
        "minute": 7,
        "ownGoal": true,
        "penalty": false
      },
      {
        "team": "USA",
        "player": "Folarin Balogun",
        "minute": 31,
        "ownGoal": false,
        "penalty": false
      },
      {
        "team": "USA",
        "player": "Folarin Balogun",
        "minute": 45,
        "ownGoal": false,
        "penalty": false
      },
      {
        "team": "USA",
        "player": "Giovanni Reyna",
        "minute": 90,
        "ownGoal": false,
        "penalty": false
      },
      {
        "team": "Paraguay",
        "player": "Mauricio",
        "minute": 73,
        "ownGoal": false,
        "penalty": false
      }
    ],
    "candidateMatches": [],
    "type": [],
    "tags": [
      "Banger"
    ],
    "pinnedTags": [
      "Banger"
    ],
    "suppressedTags": [],
    "importance": null,
    "note": "",
    "backup": "",
    "metadataConfidence": {
      "match": 1,
      "teams": 1,
      "stage": 1,
      "score": 1
    },
    "needsReview": false
  },
  {
    "id": "347f689dac00",
    "title": "César Montes (Mexico) straight red card against South Africa 90+2'",
    "url": "https://www.reddit.com/r/soccer/comments/1u3b9rw/c%C3%A9sar_montes_mexico_straight_red_card_against",
    "canonicalUrl": "https://www.reddit.com/r/soccer/comments/1u3b9rw",
    "source": "Reddit",
    "sourceDetail": "r/soccer",
    "description": null,
    "thumbnailRemoteUrl": "data:image/svg+xml;utf8,%3Csvg%20xmlns%3D%22http%3A%2F%2Fwww.w3.org%2F2000%2Fsvg%22%20width%3D%22120%22%20height%3D%22120%22%20viewBox%3D%220%200%20120%20120%22%3E%3Crect%20width%3D%22120%22%20height%3D%22120%22%20rx%3D%2216%22%20fill%3D%22%23ff4500%22%2F%3E%3Ccircle%20cx%3D%2260%22%20cy%3D%2266%22%20r%3D%2234%22%20fill%3D%22%23fff%22%2F%3E%3Ccircle%20cx%3D%2246%22%20cy%3D%2264%22%20r%3D%226%22%20fill%3D%22%23ff4500%22%2F%3E%3Ccircle%20cx%3D%2274%22%20cy%3D%2264%22%20r%3D%226%22%20fill%3D%22%23ff4500%22%2F%3E%3Cpath%20d%3D%22M44%2080%20q16%2012%2032%200%22%20stroke%3D%22%23ff4500%22%20stroke-width%3D%225%22%20fill%3D%22none%22%20stroke-linecap%3D%22round%22%2F%3E%3C%2Fsvg%3E",
    "thumbnailLocalPath": null,
    "externalUrl": null,
    "archivedUrl": null,
    "postDate": null,
    "dateSaved": "2026-06-15T12:45:55Z",
    "matchId": "MEX-RSA-2026-06-11",
    "matchLabel": "🇲🇽 Mexico vs 🇿🇦 South Africa",
    "stage": "Group stage",
    "group": "A",
    "teams": [
      "Mexico",
      "South Africa"
    ],
    "teamCodes": [
      "MEX",
      "RSA"
    ],
    "scoreLabel": "🇲🇽 Mexico 2–0 🇿🇦 South Africa",
    "goals": [
      {
        "team": "Mexico",
        "player": "Julián Quiñones",
        "minute": 9,
        "ownGoal": false,
        "penalty": false
      },
      {
        "team": "Mexico",
        "player": "Raúl Jiménez",
        "minute": 67,
        "ownGoal": false,
        "penalty": false
      }
    ],
    "candidateMatches": [],
    "type": [],
    "tags": [
      "Red card"
    ],
    "pinnedTags": [
      "Red card"
    ],
    "suppressedTags": [],
    "importance": null,
    "note": "",
    "backup": "",
    "metadataConfidence": {
      "match": 1,
      "teams": 1,
      "stage": 1,
      "score": 1
    },
    "needsReview": false
  },
  {
    "id": "dbb31e90f48b",
    "title": "[WC2026 Matchday 2] All Goals with Scoring Nation Commentary",
    "url": "https://www.reddit.com/r/soccer/comments/1u4kg9j/wc2026_matchday_2_all_goals_with_scoring_nation",
    "canonicalUrl": "https://www.reddit.com/r/soccer/comments/1u4kg9j",
    "source": "Reddit",
    "sourceDetail": "r/soccer",
    "description": null,
    "thumbnailRemoteUrl": "data:image/svg+xml;utf8,%3Csvg%20xmlns%3D%22http%3A%2F%2Fwww.w3.org%2F2000%2Fsvg%22%20width%3D%22120%22%20height%3D%22120%22%20viewBox%3D%220%200%20120%20120%22%3E%3Crect%20width%3D%22120%22%20height%3D%22120%22%20rx%3D%2216%22%20fill%3D%22%23ff4500%22%2F%3E%3Ccircle%20cx%3D%2260%22%20cy%3D%2266%22%20r%3D%2234%22%20fill%3D%22%23fff%22%2F%3E%3Ccircle%20cx%3D%2246%22%20cy%3D%2264%22%20r%3D%226%22%20fill%3D%22%23ff4500%22%2F%3E%3Ccircle%20cx%3D%2274%22%20cy%3D%2264%22%20r%3D%226%22%20fill%3D%22%23ff4500%22%2F%3E%3Cpath%20d%3D%22M44%2080%20q16%2012%2032%200%22%20stroke%3D%22%23ff4500%22%20stroke-width%3D%225%22%20fill%3D%22none%22%20stroke-linecap%3D%22round%22%2F%3E%3C%2Fsvg%3E",
    "thumbnailLocalPath": null,
    "externalUrl": null,
    "archivedUrl": null,
    "postDate": null,
    "dateSaved": "2026-06-15T12:46:52Z",
    "matchId": null,
    "matchLabel": null,
    "stage": "Group stage",
    "group": null,
    "teams": [],
    "teamCodes": [],
    "scoreLabel": null,
    "goals": [],
    "candidateMatches": [],
    "type": [],
    "tags": [
      "Highlights"
    ],
    "pinnedTags": [],
    "suppressedTags": [],
    "importance": null,
    "note": "",
    "backup": "",
    "metadataConfidence": {
      "match": 0,
      "teams": 0,
      "stage": 0.7,
      "score": 0
    },
    "needsReview": false,
    "matchLocked": true
  },
  {
    "id": "faf8eaad4300",
    "title": "Korea Republic 0-1  Czech Republic - Ladislav Krejci 59'",
    "url": "https://www.reddit.com/r/soccer/comments/1u3jtvz/korea_republic_01_czech_republic_ladislav_krejci",
    "canonicalUrl": "https://www.reddit.com/r/soccer/comments/1u3jtvz",
    "source": "Reddit",
    "sourceDetail": "r/soccer",
    "description": null,
    "thumbnailRemoteUrl": "data:image/svg+xml;utf8,%3Csvg%20xmlns%3D%22http%3A%2F%2Fwww.w3.org%2F2000%2Fsvg%22%20width%3D%22120%22%20height%3D%22120%22%20viewBox%3D%220%200%20120%20120%22%3E%3Crect%20width%3D%22120%22%20height%3D%22120%22%20rx%3D%2216%22%20fill%3D%22%23ff4500%22%2F%3E%3Ccircle%20cx%3D%2260%22%20cy%3D%2266%22%20r%3D%2234%22%20fill%3D%22%23fff%22%2F%3E%3Ccircle%20cx%3D%2246%22%20cy%3D%2264%22%20r%3D%226%22%20fill%3D%22%23ff4500%22%2F%3E%3Ccircle%20cx%3D%2274%22%20cy%3D%2264%22%20r%3D%226%22%20fill%3D%22%23ff4500%22%2F%3E%3Cpath%20d%3D%22M44%2080%20q16%2012%2032%200%22%20stroke%3D%22%23ff4500%22%20stroke-width%3D%225%22%20fill%3D%22none%22%20stroke-linecap%3D%22round%22%2F%3E%3C%2Fsvg%3E",
    "thumbnailLocalPath": null,
    "externalUrl": null,
    "archivedUrl": null,
    "postDate": null,
    "dateSaved": "2026-06-15T12:47:34Z",
    "matchId": "KOR-CZE-2026-06-11",
    "matchLabel": "🇰🇷 South Korea vs 🇨🇿 Czech Republic",
    "stage": "Group stage",
    "group": "A",
    "teams": [
      "South Korea",
      "Czech Republic"
    ],
    "teamCodes": [
      "KOR",
      "CZE"
    ],
    "scoreLabel": "🇰🇷 South Korea 2–1 🇨🇿 Czech Republic",
    "goals": [
      {
        "team": "South Korea",
        "player": "Hwang In-Beom",
        "minute": 67,
        "ownGoal": false,
        "penalty": false
      },
      {
        "team": "South Korea",
        "player": "Oh Hyeon-Gyu",
        "minute": 80,
        "ownGoal": false,
        "penalty": false
      },
      {
        "team": "Czech Republic",
        "player": "Ladislav Krejcí",
        "minute": 59,
        "ownGoal": false,
        "penalty": false
      }
    ],
    "candidateMatches": [],
    "type": [],
    "tags": [
      "Goal",
      "Highlights"
    ],
    "pinnedTags": [],
    "suppressedTags": [],
    "importance": null,
    "note": "",
    "backup": "",
    "metadataConfidence": {
      "match": 1,
      "teams": 1,
      "stage": 1,
      "score": 1
    },
    "needsReview": false
  },
  {
    "id": "d278a5177f8a",
    "title": "Referee Wilton Pereira Sampaio explains the VAR decision to show a South African player a red card in the match against Mexico",
    "url": "https://www.reddit.com/r/soccer/comments/1u3blwm/referee_wilton_pereira_sampaio_explains_the_var",
    "canonicalUrl": "https://www.reddit.com/r/soccer/comments/1u3blwm",
    "source": "Reddit",
    "sourceDetail": "r/soccer",
    "description": null,
    "thumbnailRemoteUrl": "data:image/svg+xml;utf8,%3Csvg%20xmlns%3D%22http%3A%2F%2Fwww.w3.org%2F2000%2Fsvg%22%20width%3D%22120%22%20height%3D%22120%22%20viewBox%3D%220%200%20120%20120%22%3E%3Crect%20width%3D%22120%22%20height%3D%22120%22%20rx%3D%2216%22%20fill%3D%22%23ff4500%22%2F%3E%3Ccircle%20cx%3D%2260%22%20cy%3D%2266%22%20r%3D%2234%22%20fill%3D%22%23fff%22%2F%3E%3Ccircle%20cx%3D%2246%22%20cy%3D%2264%22%20r%3D%226%22%20fill%3D%22%23ff4500%22%2F%3E%3Ccircle%20cx%3D%2274%22%20cy%3D%2264%22%20r%3D%226%22%20fill%3D%22%23ff4500%22%2F%3E%3Cpath%20d%3D%22M44%2080%20q16%2012%2032%200%22%20stroke%3D%22%23ff4500%22%20stroke-width%3D%225%22%20fill%3D%22none%22%20stroke-linecap%3D%22round%22%2F%3E%3C%2Fsvg%3E",
    "thumbnailLocalPath": null,
    "externalUrl": null,
    "archivedUrl": "https://web.archive.org/web/20260612025121/https://www.reddit.com/r/soccer/comments/1u3blwm/referee_wilton_pereira_sampaio_explains_the_var/",
    "postDate": null,
    "dateSaved": "2026-06-15T12:47:38Z",
    "matchId": "MEX-RSA-2026-06-11",
    "matchLabel": "🇲🇽 Mexico vs 🇿🇦 South Africa",
    "stage": "Group stage",
    "group": "A",
    "teams": [
      "Mexico",
      "South Africa"
    ],
    "teamCodes": [
      "MEX",
      "RSA"
    ],
    "scoreLabel": "🇲🇽 Mexico 2–0 🇿🇦 South Africa",
    "goals": [
      {
        "team": "Mexico",
        "player": "Julián Quiñones",
        "minute": 9,
        "ownGoal": false,
        "penalty": false
      },
      {
        "team": "Mexico",
        "player": "Raúl Jiménez",
        "minute": 67,
        "ownGoal": false,
        "penalty": false
      }
    ],
    "candidateMatches": [],
    "type": [],
    "tags": [],
    "pinnedTags": [],
    "suppressedTags": [],
    "importance": null,
    "note": "",
    "backup": "",
    "metadataConfidence": {
      "match": 1,
      "teams": 1,
      "stage": 1,
      "score": 1
    },
    "needsReview": false
  },
  {
    "id": "e8a92460bfb9",
    "title": "South Africans weren't exactly thrilled with their World Cup opener.",
    "url": "https://www.reddit.com/r/soccer/comments/1u3fwk9/south_africans_werent_exactly_thrilled_with_their",
    "canonicalUrl": "https://www.reddit.com/r/soccer/comments/1u3fwk9",
    "source": "Reddit",
    "sourceDetail": "r/soccer",
    "description": null,
    "thumbnailRemoteUrl": "data:image/svg+xml;utf8,%3Csvg%20xmlns%3D%22http%3A%2F%2Fwww.w3.org%2F2000%2Fsvg%22%20width%3D%22120%22%20height%3D%22120%22%20viewBox%3D%220%200%20120%20120%22%3E%3Crect%20width%3D%22120%22%20height%3D%22120%22%20rx%3D%2216%22%20fill%3D%22%23ff4500%22%2F%3E%3Ccircle%20cx%3D%2260%22%20cy%3D%2266%22%20r%3D%2234%22%20fill%3D%22%23fff%22%2F%3E%3Ccircle%20cx%3D%2246%22%20cy%3D%2264%22%20r%3D%226%22%20fill%3D%22%23ff4500%22%2F%3E%3Ccircle%20cx%3D%2274%22%20cy%3D%2264%22%20r%3D%226%22%20fill%3D%22%23ff4500%22%2F%3E%3Cpath%20d%3D%22M44%2080%20q16%2012%2032%200%22%20stroke%3D%22%23ff4500%22%20stroke-width%3D%225%22%20fill%3D%22none%22%20stroke-linecap%3D%22round%22%2F%3E%3C%2Fsvg%3E",
    "thumbnailLocalPath": null,
    "externalUrl": null,
    "archivedUrl": "https://web.archive.org/web/20260612150251/https://www.reddit.com/r/soccer/comments/1u3fwk9/south_africans_werent_exactly_thrilled_with_their/",
    "postDate": null,
    "dateSaved": "2026-06-15T12:47:41Z",
    "matchId": "MEX-RSA-2026-06-11",
    "matchLabel": "🇲🇽 Mexico vs 🇿🇦 South Africa",
    "stage": "Group stage",
    "group": "A",
    "teams": [
      "Mexico",
      "South Africa"
    ],
    "teamCodes": [
      "MEX",
      "RSA"
    ],
    "scoreLabel": "🇲🇽 Mexico 2–0 🇿🇦 South Africa",
    "goals": [
      {
        "team": "Mexico",
        "player": "Julián Quiñones",
        "minute": 9,
        "ownGoal": false,
        "penalty": false
      },
      {
        "team": "Mexico",
        "player": "Raúl Jiménez",
        "minute": 67,
        "ownGoal": false,
        "penalty": false
      }
    ],
    "candidateMatches": [],
    "type": [],
    "tags": [],
    "pinnedTags": [],
    "suppressedTags": [],
    "importance": null,
    "note": "",
    "backup": "",
    "metadataConfidence": {
      "match": 1,
      "teams": 1,
      "stage": 1,
      "score": 1
    },
    "needsReview": false
  },
  {
    "id": "5603b1447fab",
    "title": "Kim Seung-Gyu save against Czechia - 81'",
    "url": "https://www.reddit.com/r/soccer/comments/1u3kcrs/kim_seunggyu_save_against_czechia_81",
    "canonicalUrl": "https://www.reddit.com/r/soccer/comments/1u3kcrs",
    "source": "Reddit",
    "sourceDetail": "r/soccer",
    "description": null,
    "thumbnailRemoteUrl": "data:image/svg+xml;utf8,%3Csvg%20xmlns%3D%22http%3A%2F%2Fwww.w3.org%2F2000%2Fsvg%22%20width%3D%22120%22%20height%3D%22120%22%20viewBox%3D%220%200%20120%20120%22%3E%3Crect%20width%3D%22120%22%20height%3D%22120%22%20rx%3D%2216%22%20fill%3D%22%23ff4500%22%2F%3E%3Ccircle%20cx%3D%2260%22%20cy%3D%2266%22%20r%3D%2234%22%20fill%3D%22%23fff%22%2F%3E%3Ccircle%20cx%3D%2246%22%20cy%3D%2264%22%20r%3D%226%22%20fill%3D%22%23ff4500%22%2F%3E%3Ccircle%20cx%3D%2274%22%20cy%3D%2264%22%20r%3D%226%22%20fill%3D%22%23ff4500%22%2F%3E%3Cpath%20d%3D%22M44%2080%20q16%2012%2032%200%22%20stroke%3D%22%23ff4500%22%20stroke-width%3D%225%22%20fill%3D%22none%22%20stroke-linecap%3D%22round%22%2F%3E%3C%2Fsvg%3E",
    "thumbnailLocalPath": null,
    "externalUrl": null,
    "archivedUrl": "https://web.archive.org/web/20260612063119/https://www.reddit.com/r/soccer/comments/1u3kcrs/kim_seunggyu_save_against_czechia_81/",
    "postDate": null,
    "dateSaved": "2026-06-15T12:47:44Z",
    "matchId": "KOR-CZE-2026-06-11",
    "matchLabel": "🇰🇷 South Korea vs 🇨🇿 Czech Republic",
    "stage": "Group stage",
    "group": "A",
    "teams": [
      "South Korea",
      "Czech Republic"
    ],
    "teamCodes": [
      "KOR",
      "CZE"
    ],
    "scoreLabel": "🇰🇷 South Korea 2–1 🇨🇿 Czech Republic",
    "goals": [
      {
        "team": "South Korea",
        "player": "Hwang In-Beom",
        "minute": 67,
        "ownGoal": false,
        "penalty": false
      },
      {
        "team": "South Korea",
        "player": "Oh Hyeon-Gyu",
        "minute": 80,
        "ownGoal": false,
        "penalty": false
      },
      {
        "team": "Czech Republic",
        "player": "Ladislav Krejcí",
        "minute": 59,
        "ownGoal": false,
        "penalty": false
      }
    ],
    "candidateMatches": [],
    "type": [],
    "tags": [
      "Saves",
      "Highlights"
    ],
    "pinnedTags": [],
    "suppressedTags": [],
    "importance": null,
    "note": "",
    "backup": "",
    "metadataConfidence": {
      "match": 1,
      "teams": 1,
      "stage": 1,
      "score": 1
    },
    "needsReview": false
  },
  {
    "id": "fd6278fe4742",
    "title": "Kim Seung-Gyu (South Korea) save against Czechia 90+3'",
    "url": "https://www.reddit.com/r/soccer/comments/1u3km7g/kim_seunggyu_south_korea_save_against_czechia_903",
    "canonicalUrl": "https://www.reddit.com/r/soccer/comments/1u3km7g",
    "source": "Reddit",
    "sourceDetail": "r/soccer",
    "description": null,
    "thumbnailRemoteUrl": "data:image/svg+xml;utf8,%3Csvg%20xmlns%3D%22http%3A%2F%2Fwww.w3.org%2F2000%2Fsvg%22%20width%3D%22120%22%20height%3D%22120%22%20viewBox%3D%220%200%20120%20120%22%3E%3Crect%20width%3D%22120%22%20height%3D%22120%22%20rx%3D%2216%22%20fill%3D%22%23ff4500%22%2F%3E%3Ccircle%20cx%3D%2260%22%20cy%3D%2266%22%20r%3D%2234%22%20fill%3D%22%23fff%22%2F%3E%3Ccircle%20cx%3D%2246%22%20cy%3D%2264%22%20r%3D%226%22%20fill%3D%22%23ff4500%22%2F%3E%3Ccircle%20cx%3D%2274%22%20cy%3D%2264%22%20r%3D%226%22%20fill%3D%22%23ff4500%22%2F%3E%3Cpath%20d%3D%22M44%2080%20q16%2012%2032%200%22%20stroke%3D%22%23ff4500%22%20stroke-width%3D%225%22%20fill%3D%22none%22%20stroke-linecap%3D%22round%22%2F%3E%3C%2Fsvg%3E",
    "thumbnailLocalPath": null,
    "externalUrl": null,
    "archivedUrl": null,
    "postDate": null,
    "dateSaved": "2026-06-15T12:48:22Z",
    "matchId": "KOR-CZE-2026-06-11",
    "matchLabel": "🇰🇷 South Korea vs 🇨🇿 Czech Republic",
    "stage": "Group stage",
    "group": "A",
    "teams": [
      "South Korea",
      "Czech Republic"
    ],
    "teamCodes": [
      "KOR",
      "CZE"
    ],
    "scoreLabel": "🇰🇷 South Korea 2–1 🇨🇿 Czech Republic",
    "goals": [
      {
        "team": "South Korea",
        "player": "Hwang In-Beom",
        "minute": 67,
        "ownGoal": false,
        "penalty": false
      },
      {
        "team": "South Korea",
        "player": "Oh Hyeon-Gyu",
        "minute": 80,
        "ownGoal": false,
        "penalty": false
      },
      {
        "team": "Czech Republic",
        "player": "Ladislav Krejcí",
        "minute": 59,
        "ownGoal": false,
        "penalty": false
      }
    ],
    "candidateMatches": [],
    "type": [],
    "tags": [
      "Saves",
      "Highlights"
    ],
    "pinnedTags": [],
    "suppressedTags": [],
    "importance": null,
    "note": "",
    "backup": "",
    "metadataConfidence": {
      "match": 1,
      "teams": 1,
      "stage": 1,
      "score": 1
    },
    "needsReview": false
  },
  {
    "id": "79c32c03c19e",
    "title": "Australia [1] - 0 Turkiye - Nystrom Irankunda 27'",
    "url": "https://www.reddit.com/r/soccer/comments/1u5bgkp/australia_1_0_turkiye_nystrom_irankunda_27",
    "canonicalUrl": "https://www.reddit.com/r/soccer/comments/1u5bgkp",
    "source": "Reddit",
    "sourceDetail": "r/soccer",
    "description": null,
    "thumbnailRemoteUrl": "data:image/svg+xml;utf8,%3Csvg%20xmlns%3D%22http%3A%2F%2Fwww.w3.org%2F2000%2Fsvg%22%20width%3D%22120%22%20height%3D%22120%22%20viewBox%3D%220%200%20120%20120%22%3E%3Crect%20width%3D%22120%22%20height%3D%22120%22%20rx%3D%2216%22%20fill%3D%22%23ff4500%22%2F%3E%3Ccircle%20cx%3D%2260%22%20cy%3D%2266%22%20r%3D%2234%22%20fill%3D%22%23fff%22%2F%3E%3Ccircle%20cx%3D%2246%22%20cy%3D%2264%22%20r%3D%226%22%20fill%3D%22%23ff4500%22%2F%3E%3Ccircle%20cx%3D%2274%22%20cy%3D%2264%22%20r%3D%226%22%20fill%3D%22%23ff4500%22%2F%3E%3Cpath%20d%3D%22M44%2080%20q16%2012%2032%200%22%20stroke%3D%22%23ff4500%22%20stroke-width%3D%225%22%20fill%3D%22none%22%20stroke-linecap%3D%22round%22%2F%3E%3C%2Fsvg%3E",
    "thumbnailLocalPath": null,
    "externalUrl": null,
    "archivedUrl": "https://web.archive.org/web/20260614051652/https://www.reddit.com/r/soccer/comments/1u5bgkp/australia_1_0_turkiye_nystrom_irankunda_27/",
    "postDate": null,
    "dateSaved": "2026-06-15T12:55:51Z",
    "matchId": "AUS-TUR-2026-06-13",
    "matchLabel": "🇦🇺 Australia vs 🇹🇷 Turkey",
    "stage": "Group stage",
    "group": "D",
    "teams": [
      "Australia",
      "Turkey"
    ],
    "teamCodes": [
      "AUS",
      "TUR"
    ],
    "scoreLabel": "🇦🇺 Australia 2–0 🇹🇷 Turkey",
    "goals": [
      {
        "team": "Australia",
        "player": "Nestory Irankunda",
        "minute": 27,
        "ownGoal": false,
        "penalty": false
      },
      {
        "team": "Australia",
        "player": "Connor Metcalfe",
        "minute": 75,
        "ownGoal": false,
        "penalty": false
      }
    ],
    "candidateMatches": [],
    "type": [],
    "tags": [
      "Goal",
      "Highlights",
      "Banger"
    ],
    "pinnedTags": [
      "Banger"
    ],
    "suppressedTags": [],
    "importance": null,
    "note": "",
    "backup": "",
    "metadataConfidence": {
      "match": 1,
      "teams": 1,
      "stage": 1,
      "score": 1
    },
    "needsReview": false
  },
  {
    "id": "ef8385a70f9a",
    "title": "Australia [2] - 0 Turkey - Connor Metcalfe  75'",
    "url": "https://www.reddit.com/r/soccer/comments/1u5cngy/australia_2_0_turkey_connor_metcalfe_75",
    "canonicalUrl": "https://www.reddit.com/r/soccer/comments/1u5cngy",
    "source": "Reddit",
    "sourceDetail": "r/soccer",
    "description": null,
    "thumbnailRemoteUrl": "data:image/svg+xml;utf8,%3Csvg%20xmlns%3D%22http%3A%2F%2Fwww.w3.org%2F2000%2Fsvg%22%20width%3D%22120%22%20height%3D%22120%22%20viewBox%3D%220%200%20120%20120%22%3E%3Crect%20width%3D%22120%22%20height%3D%22120%22%20rx%3D%2216%22%20fill%3D%22%23ff4500%22%2F%3E%3Ccircle%20cx%3D%2260%22%20cy%3D%2266%22%20r%3D%2234%22%20fill%3D%22%23fff%22%2F%3E%3Ccircle%20cx%3D%2246%22%20cy%3D%2264%22%20r%3D%226%22%20fill%3D%22%23ff4500%22%2F%3E%3Ccircle%20cx%3D%2274%22%20cy%3D%2264%22%20r%3D%226%22%20fill%3D%22%23ff4500%22%2F%3E%3Cpath%20d%3D%22M44%2080%20q16%2012%2032%200%22%20stroke%3D%22%23ff4500%22%20stroke-width%3D%225%22%20fill%3D%22none%22%20stroke-linecap%3D%22round%22%2F%3E%3C%2Fsvg%3E",
    "thumbnailLocalPath": null,
    "externalUrl": null,
    "archivedUrl": "https://web.archive.org/web/20260614055020/https://www.reddit.com/r/soccer/comments/1u5cngy/australia_2_0_turkey_connor_metcalfe_75/",
    "postDate": null,
    "dateSaved": "2026-06-15T12:55:54Z",
    "matchId": "AUS-TUR-2026-06-13",
    "matchLabel": "🇦🇺 Australia vs 🇹🇷 Turkey",
    "stage": "Group stage",
    "group": "D",
    "teams": [
      "Australia",
      "Turkey"
    ],
    "teamCodes": [
      "AUS",
      "TUR"
    ],
    "scoreLabel": "🇦🇺 Australia 2–0 🇹🇷 Turkey",
    "goals": [
      {
        "team": "Australia",
        "player": "Nestory Irankunda",
        "minute": 27,
        "ownGoal": false,
        "penalty": false
      },
      {
        "team": "Australia",
        "player": "Connor Metcalfe",
        "minute": 75,
        "ownGoal": false,
        "penalty": false
      }
    ],
    "candidateMatches": [],
    "type": [],
    "tags": [
      "Goal",
      "Highlights",
      "Banger"
    ],
    "pinnedTags": [
      "Banger"
    ],
    "suppressedTags": [],
    "importance": null,
    "note": "",
    "backup": "",
    "metadataConfidence": {
      "match": 1,
      "teams": 1,
      "stage": 1,
      "score": 1
    },
    "needsReview": false
  },
  {
    "id": "b716583130ae",
    "title": "Brazil 0 - [1] Morocco - Saibari I. 20'",
    "url": "https://www.reddit.com/r/soccer/comments/1u53yv5/brazil_0_1_morocco_saibari_i_20",
    "canonicalUrl": "https://www.reddit.com/r/soccer/comments/1u53yv5",
    "source": "Reddit",
    "sourceDetail": "r/soccer",
    "description": null,
    "thumbnailRemoteUrl": "data:image/svg+xml;utf8,%3Csvg%20xmlns%3D%22http%3A%2F%2Fwww.w3.org%2F2000%2Fsvg%22%20width%3D%22120%22%20height%3D%22120%22%20viewBox%3D%220%200%20120%20120%22%3E%3Crect%20width%3D%22120%22%20height%3D%22120%22%20rx%3D%2216%22%20fill%3D%22%23ff4500%22%2F%3E%3Ccircle%20cx%3D%2260%22%20cy%3D%2266%22%20r%3D%2234%22%20fill%3D%22%23fff%22%2F%3E%3Ccircle%20cx%3D%2246%22%20cy%3D%2264%22%20r%3D%226%22%20fill%3D%22%23ff4500%22%2F%3E%3Ccircle%20cx%3D%2274%22%20cy%3D%2264%22%20r%3D%226%22%20fill%3D%22%23ff4500%22%2F%3E%3Cpath%20d%3D%22M44%2080%20q16%2012%2032%200%22%20stroke%3D%22%23ff4500%22%20stroke-width%3D%225%22%20fill%3D%22none%22%20stroke-linecap%3D%22round%22%2F%3E%3C%2Fsvg%3E",
    "thumbnailLocalPath": null,
    "externalUrl": null,
    "archivedUrl": "https://web.archive.org/web/20260614010744/https://www.reddit.com/r/soccer/comments/1u53yv5/brazil_0_1_morocco_saibari_i_20/",
    "postDate": null,
    "dateSaved": "2026-06-15T12:55:57Z",
    "matchId": "BRA-MAR-2026-06-13",
    "matchLabel": "🇧🇷 Brazil vs 🇲🇦 Morocco",
    "stage": "Group stage",
    "group": "C",
    "teams": [
      "Brazil",
      "Morocco"
    ],
    "teamCodes": [
      "BRA",
      "MAR"
    ],
    "scoreLabel": "🇧🇷 Brazil 1–1 🇲🇦 Morocco",
    "goals": [
      {
        "team": "Brazil",
        "player": "Vinícius Júnior",
        "minute": 32,
        "ownGoal": false,
        "penalty": false
      },
      {
        "team": "Morocco",
        "player": "Ismael Saibari",
        "minute": 21,
        "ownGoal": false,
        "penalty": false
      }
    ],
    "candidateMatches": [],
    "type": [],
    "tags": [
      "Goal",
      "Highlights",
      "Banger"
    ],
    "pinnedTags": [
      "Banger"
    ],
    "suppressedTags": [],
    "importance": null,
    "note": "",
    "backup": "",
    "metadataConfidence": {
      "match": 1,
      "teams": 1,
      "stage": 1,
      "score": 1
    },
    "needsReview": false
  },
  {
    "id": "f295cc5c1496",
    "title": "Brazil [1] - 1 Morocco - Vinícius Júnior 32'",
    "url": "https://www.reddit.com/r/soccer/comments/1u547jh/brazil_1_1_morocco_vin%C3%ADcius_j%C3%BAnior_32",
    "canonicalUrl": "https://www.reddit.com/r/soccer/comments/1u547jh",
    "source": "Reddit",
    "sourceDetail": "r/soccer",
    "description": null,
    "thumbnailRemoteUrl": "data:image/svg+xml;utf8,%3Csvg%20xmlns%3D%22http%3A%2F%2Fwww.w3.org%2F2000%2Fsvg%22%20width%3D%22120%22%20height%3D%22120%22%20viewBox%3D%220%200%20120%20120%22%3E%3Crect%20width%3D%22120%22%20height%3D%22120%22%20rx%3D%2216%22%20fill%3D%22%23ff4500%22%2F%3E%3Ccircle%20cx%3D%2260%22%20cy%3D%2266%22%20r%3D%2234%22%20fill%3D%22%23fff%22%2F%3E%3Ccircle%20cx%3D%2246%22%20cy%3D%2264%22%20r%3D%226%22%20fill%3D%22%23ff4500%22%2F%3E%3Ccircle%20cx%3D%2274%22%20cy%3D%2264%22%20r%3D%226%22%20fill%3D%22%23ff4500%22%2F%3E%3Cpath%20d%3D%22M44%2080%20q16%2012%2032%200%22%20stroke%3D%22%23ff4500%22%20stroke-width%3D%225%22%20fill%3D%22none%22%20stroke-linecap%3D%22round%22%2F%3E%3C%2Fsvg%3E",
    "thumbnailLocalPath": null,
    "externalUrl": null,
    "archivedUrl": null,
    "postDate": null,
    "dateSaved": "2026-06-15T12:56:39Z",
    "matchId": "BRA-MAR-2026-06-13",
    "matchLabel": "🇧🇷 Brazil vs 🇲🇦 Morocco",
    "stage": "Group stage",
    "group": "C",
    "teams": [
      "Brazil",
      "Morocco"
    ],
    "teamCodes": [
      "BRA",
      "MAR"
    ],
    "scoreLabel": "🇧🇷 Brazil 1–1 🇲🇦 Morocco",
    "goals": [
      {
        "team": "Brazil",
        "player": "Vinícius Júnior",
        "minute": 32,
        "ownGoal": false,
        "penalty": false
      },
      {
        "team": "Morocco",
        "player": "Ismael Saibari",
        "minute": 21,
        "ownGoal": false,
        "penalty": false
      }
    ],
    "candidateMatches": [],
    "type": [],
    "tags": [
      "Goal",
      "Highlights",
      "Banger"
    ],
    "pinnedTags": [
      "Banger"
    ],
    "suppressedTags": [],
    "importance": null,
    "note": "",
    "backup": "",
    "metadataConfidence": {
      "match": 1,
      "teams": 1,
      "stage": 1,
      "score": 1
    },
    "needsReview": false
  },
  {
    "id": "2fbd38876fc0",
    "title": "A Mexican fan sneaked tequila into the stadium in a flask disguised as a mobile",
    "url": "https://www.reddit.com/r/soccer/comments/1u5i4zl/a_mexican_fan_sneaked_tequila_into_the_stadium_in",
    "canonicalUrl": "https://www.reddit.com/r/soccer/comments/1u5i4zl/a_mexican_fan_sneaked_tequila_into_the_stadium_in/",
    "source": "Reddit",
    "sourceDetail": "r/soccer",
    "description": "Posted in r/soccer by u/OkayFine101 • 5,782 points and 121 comments",
    "thumbnailRemoteUrl": "https://external-preview.redd.it/ZXhucmR3YnpiODdoMQUTAZLZxCKyVHvQHF3R6GntJXVKQqCQkCYuvT8EKyyd.png?width=140&height=140&crop=1:1,smart&format=jpg&auto=webp",
    "thumbnailLocalPath": null,
    "externalUrl": null,
    "archivedUrl": "https://web.archive.org/web/20260615000345/https://www.reddit.com/r/soccer/comments/1u5i4zl/a_mexican_fan_sneaked_tequila_into_the_stadium_in/",
    "postDate": "2026-06-14T10:59:15Z",
    "dateSaved": "2026-06-15T12:56:55Z",
    "matchId": null,
    "matchLabel": null,
    "stage": null,
    "group": null,
    "teams": [],
    "teamCodes": [],
    "scoreLabel": null,
    "goals": [],
    "candidateMatches": [],
    "type": [],
    "tags": [
      "Vibes"
    ],
    "pinnedTags": [
      "Vibes"
    ],
    "suppressedTags": [],
    "importance": null,
    "note": "",
    "backup": "",
    "metadataConfidence": {
      "match": 0,
      "teams": 0,
      "stage": 0,
      "score": 0
    },
    "needsReview": false
  },
  {
    "id": "a3d3fb755989",
    "title": "Rendition of Scotland’s anthem “Flowers of Scotland” before the start of the match",
    "url": "https://www.reddit.com/r/soccer/comments/1u57fpe/rendition_of_scotlands_anthem_flowers_of_scotland",
    "canonicalUrl": "https://www.reddit.com/r/soccer/comments/1u57fpe/rendition_of_scotlands_anthem_flowers_of_scotland/",
    "source": "Reddit",
    "sourceDetail": "r/soccer",
    "description": "Posted in r/soccer by u/Critical_Mountain851 • 5,951 points and 606 comments",
    "thumbnailRemoteUrl": "https://external-preview.redd.it/bGNqdjIxaDBmNTdoMZ-Dsf-sUIPw9RTNCOn3XOJEOSQNQ_f7G0uroW2MwA6P.png?width=140&height=78&format=jpg&auto=webp",
    "thumbnailLocalPath": null,
    "externalUrl": null,
    "archivedUrl": null,
    "postDate": "2026-06-14T01:10:02Z",
    "dateSaved": "2026-06-15T12:57:34Z",
    "matchId": "HAI-SCO-2026-06-13",
    "matchLabel": "🇭🇹 Haiti vs 🏴󠁧󠁢󠁳󠁣󠁴󠁿 Scotland",
    "stage": "Group stage",
    "group": "C",
    "teams": [
      "Haiti",
      "Scotland"
    ],
    "teamCodes": [
      "HAI",
      "SCO"
    ],
    "scoreLabel": "🇭🇹 Haiti 0–1 🏴󠁧󠁢󠁳󠁣󠁴󠁿 Scotland",
    "goals": [
      {
        "team": "Scotland",
        "player": "John McGinn",
        "minute": 28,
        "ownGoal": false,
        "penalty": false
      }
    ],
    "candidateMatches": [],
    "type": [],
    "tags": [
      "Vibes"
    ],
    "pinnedTags": [
      "Vibes"
    ],
    "suppressedTags": [],
    "importance": null,
    "note": "",
    "backup": "",
    "metadataConfidence": {
      "match": 1,
      "teams": 1,
      "stage": 1,
      "score": 1
    },
    "needsReview": false
  },
  {
    "id": "515197642b96",
    "title": "Loch Lomond sung by the Tartan Army before kick off",
    "url": "https://www.reddit.com/r/soccer/comments/1u5ine6/loch_lomond_sung_by_the_tartan_army_before_kick",
    "canonicalUrl": "https://www.reddit.com/r/soccer/comments/1u5ine6/loch_lomond_sung_by_the_tartan_army_before_kick/",
    "source": "Reddit",
    "sourceDetail": "r/soccer",
    "description": "Posted in r/soccer by u/Longjumping-Move-356 • 951 points and 154 comments",
    "thumbnailRemoteUrl": "https://external-preview.redd.it/M3AwaGN5eDJoODdoMa7mWh2eYrIc3NYytmDDyXcAMEGkMUBAOpFM5luby6bx.png?width=140&height=140&crop=1:1,smart&format=jpg&auto=webp",
    "thumbnailLocalPath": null,
    "externalUrl": null,
    "archivedUrl": null,
    "postDate": "2026-06-14T11:27:02Z",
    "dateSaved": "2026-06-15T12:58:14Z",
    "matchId": "HAI-SCO-2026-06-13",
    "matchLabel": "🇭🇹 Haiti vs 🏴󠁧󠁢󠁳󠁣󠁴󠁿 Scotland",
    "stage": "Group stage",
    "group": "C",
    "teams": [
      "Haiti",
      "Scotland"
    ],
    "teamCodes": [
      "HAI",
      "SCO"
    ],
    "scoreLabel": "🇭🇹 Haiti 0–1 🏴󠁧󠁢󠁳󠁣󠁴󠁿 Scotland",
    "goals": [
      {
        "team": "Scotland",
        "player": "John McGinn",
        "minute": 28,
        "ownGoal": false,
        "penalty": false
      }
    ],
    "candidateMatches": [],
    "type": [],
    "tags": [
      "Vibes"
    ],
    "pinnedTags": [
      "Vibes"
    ],
    "suppressedTags": [],
    "importance": null,
    "note": "",
    "backup": "",
    "metadataConfidence": {
      "match": 1,
      "teams": 1,
      "stage": 1,
      "score": 1
    },
    "needsReview": false
  },
  {
    "id": "97f152fe9e60",
    "title": "Boston police officer showing off his skill",
    "url": "https://www.reddit.com/r/soccer/comments/1u4s128/boston_police_officer_showing_off_his_skill",
    "canonicalUrl": "https://www.reddit.com/r/soccer/comments/1u4s128/boston_police_officer_showing_off_his_skill/",
    "source": "Reddit",
    "sourceDetail": "r/soccer",
    "description": "Posted in r/soccer by u/IncidentVarious1530 • 14,275 points and 333 comments",
    "thumbnailRemoteUrl": "https://external-preview.redd.it/M3lxYzZmYnI1MjdoMULR8OrBqI0fW8G74njHEB-V7EyJRa7eYVymFbzqYbTN.png?width=140&height=140&crop=1:1,smart&format=jpg&auto=webp",
    "thumbnailLocalPath": null,
    "externalUrl": null,
    "archivedUrl": null,
    "postDate": "2026-06-13T14:12:49Z",
    "dateSaved": "2026-06-15T12:58:58Z",
    "matchId": null,
    "matchLabel": null,
    "stage": null,
    "group": null,
    "teams": [],
    "teamCodes": [],
    "scoreLabel": null,
    "goals": [],
    "candidateMatches": [],
    "type": [],
    "tags": [
      "Vibes"
    ],
    "pinnedTags": [
      "Vibes"
    ],
    "suppressedTags": [],
    "importance": null,
    "note": "",
    "backup": "",
    "metadataConfidence": {
      "match": 0,
      "teams": 0,
      "stage": 0,
      "score": 0
    },
    "needsReview": false
  },
  {
    "id": "370cac244f55",
    "title": "Mexican commentators react to Folarin Balogun's second goal: \"Oh my fucking goodness!\"",
    "url": "https://www.reddit.com/r/soccer/comments/1u4s85x/mexican_commentators_react_to_folarin_baloguns",
    "canonicalUrl": "https://www.reddit.com/r/soccer/comments/1u4s85x/mexican_commentators_react_to_folarin_baloguns/",
    "source": "Reddit",
    "sourceDetail": "r/soccer",
    "description": "Posted in r/soccer by u/TomasRoncero • 5,660 points and 156 comments",
    "thumbnailRemoteUrl": "https://external-preview.redd.it/ejJlb2Z4bDg3MjdoMeyXeskIy43jmEEphl7R3iJ1OoSfUQlwWmAQbfa4TYXp.png?width=140&height=77&format=jpg&auto=webp",
    "thumbnailLocalPath": null,
    "externalUrl": null,
    "archivedUrl": null,
    "postDate": "2026-06-13T14:21:08Z",
    "dateSaved": "2026-06-15T12:59:41Z",
    "matchId": null,
    "matchLabel": null,
    "stage": null,
    "group": null,
    "teams": [],
    "teamCodes": [],
    "scoreLabel": null,
    "goals": [],
    "candidateMatches": [],
    "type": [],
    "tags": [
      "Vibes"
    ],
    "pinnedTags": [
      "Vibes"
    ],
    "suppressedTags": [],
    "importance": null,
    "note": "",
    "backup": "",
    "metadataConfidence": {
      "match": 0,
      "teams": 0,
      "stage": 0,
      "score": 0
    },
    "needsReview": false
  },
  {
    "id": "69b19a591e42",
    "title": "Melbourne erupts as Australia go 1-0 up vs Turkey",
    "url": "https://www.reddit.com/r/soccer/comments/1u5g0ko/melbourne_erupts_as_australia_go_10_up_vs_turkey",
    "canonicalUrl": "https://www.reddit.com/r/soccer/comments/1u5g0ko/melbourne_erupts_as_australia_go_10_up_vs_turkey/",
    "source": "Reddit",
    "sourceDetail": "r/soccer",
    "description": "Posted in r/soccer by u/OkayFine101 • 3,490 points and 187 comments",
    "thumbnailRemoteUrl": "https://external-preview.redd.it/Z242Y2x5cmRwNzdoMTAw2SijA7IJ6x6CyjvpWAt0wueoLmO-iB6FtXe-HEuf.png?width=140&height=78&format=jpg&auto=webp",
    "thumbnailLocalPath": null,
    "externalUrl": null,
    "archivedUrl": null,
    "postDate": "2026-06-14T08:52:14Z",
    "dateSaved": "2026-06-15T13:01:07Z",
    "matchId": "AUS-TUR-2026-06-13",
    "matchLabel": "🇦🇺 Australia vs 🇹🇷 Turkey",
    "stage": "Group stage",
    "group": "D",
    "teams": [
      "Australia",
      "Turkey"
    ],
    "teamCodes": [
      "AUS",
      "TUR"
    ],
    "scoreLabel": "🇦🇺 Australia 2–0 🇹🇷 Turkey",
    "goals": [
      {
        "team": "Australia",
        "player": "Nestory Irankunda",
        "minute": 27,
        "ownGoal": false,
        "penalty": false
      },
      {
        "team": "Australia",
        "player": "Connor Metcalfe",
        "minute": 75,
        "ownGoal": false,
        "penalty": false
      }
    ],
    "candidateMatches": [],
    "type": [],
    "tags": [],
    "pinnedTags": [],
    "suppressedTags": [],
    "importance": null,
    "note": "",
    "backup": "",
    "metadataConfidence": {
      "match": 1,
      "teams": 1,
      "stage": 1,
      "score": 1
    },
    "needsReview": false
  },
  {
    "id": "bb4fd498c297",
    "title": "Australia vs Turkiye - Patrick Beach diving save 30'",
    "url": "https://www.reddit.com/r/soccer/comments/1u5c13d/australia_vs_turkiye_patrick_beach_diving_save_30",
    "canonicalUrl": "https://www.reddit.com/r/soccer/comments/1u5c13d/australia_vs_turkiye_patrick_beach_diving_save_30/",
    "source": "Reddit",
    "sourceDetail": "r/soccer",
    "description": "Posted in r/soccer by u/Moose4KU • 4,939 points and 95 comments",
    "thumbnailRemoteUrl": "https://external-preview.redd.it/eXlwemE3OGJrNjdoMakLOfvurGWK641QY7E3Ai2p9--2_3i7DRXnpgyQVLO4.png?width=140&height=78&format=jpg&auto=webp",
    "thumbnailLocalPath": null,
    "externalUrl": null,
    "archivedUrl": "https://web.archive.org/web/20260614072220/https://www.reddit.com/r/soccer/comments/1u5c13d/australia_vs_turkiye_patrick_beach_diving_save_30/",
    "postDate": "2026-06-14T05:01:37Z",
    "dateSaved": "2026-06-15T13:01:10Z",
    "matchId": "AUS-TUR-2026-06-13",
    "matchLabel": "🇦🇺 Australia vs 🇹🇷 Turkey",
    "stage": "Group stage",
    "group": "D",
    "teams": [
      "Australia",
      "Turkey"
    ],
    "teamCodes": [
      "AUS",
      "TUR"
    ],
    "scoreLabel": "🇦🇺 Australia 2–0 🇹🇷 Turkey",
    "goals": [
      {
        "team": "Australia",
        "player": "Nestory Irankunda",
        "minute": 27,
        "ownGoal": false,
        "penalty": false
      },
      {
        "team": "Australia",
        "player": "Connor Metcalfe",
        "minute": 75,
        "ownGoal": false,
        "penalty": false
      }
    ],
    "candidateMatches": [],
    "type": [],
    "tags": [
      "Saves",
      "Highlights"
    ],
    "pinnedTags": [],
    "suppressedTags": [],
    "importance": null,
    "note": "",
    "backup": "",
    "metadataConfidence": {
      "match": 1,
      "teams": 1,
      "stage": 1,
      "score": 1
    },
    "needsReview": false
  },
  {
    "id": "faf7cdff748c",
    "title": "Momentum Index at 93' Turkey vs Australia",
    "url": "https://www.reddit.com/r/soccer/comments/1u5d0dw/momentum_index_at_93_turkey_vs_australia",
    "canonicalUrl": "https://www.reddit.com/r/soccer/comments/1u5d0dw/momentum_index_at_93_turkey_vs_australia/",
    "source": "Reddit",
    "sourceDetail": "r/soccer",
    "description": "Posted in r/soccer by u/IamBrazilian_AMA • 3,528 points and 357 comments",
    "thumbnailRemoteUrl": "https://preview.redd.it/5qyubv5mt67h1.png?width=140&height=83&auto=webp",
    "thumbnailLocalPath": null,
    "externalUrl": null,
    "archivedUrl": null,
    "postDate": "2026-06-14T05:55:26Z",
    "dateSaved": "2026-06-15T13:01:53Z",
    "matchId": "AUS-TUR-2026-06-13",
    "matchLabel": "🇦🇺 Australia vs 🇹🇷 Turkey",
    "stage": "Group stage",
    "group": "D",
    "teams": [
      "Australia",
      "Turkey"
    ],
    "teamCodes": [
      "AUS",
      "TUR"
    ],
    "scoreLabel": "🇦🇺 Australia 2–0 🇹🇷 Turkey",
    "goals": [
      {
        "team": "Australia",
        "player": "Nestory Irankunda",
        "minute": 27,
        "ownGoal": false,
        "penalty": false
      },
      {
        "team": "Australia",
        "player": "Connor Metcalfe",
        "minute": 75,
        "ownGoal": false,
        "penalty": false
      }
    ],
    "candidateMatches": [],
    "type": [],
    "tags": [],
    "pinnedTags": [],
    "suppressedTags": [],
    "importance": null,
    "note": "",
    "backup": "",
    "metadataConfidence": {
      "match": 1,
      "teams": 1,
      "stage": 1,
      "score": 1
    },
    "needsReview": false
  },
  {
    "id": "1ad4d7af133e",
    "title": "Watch party in Turkey, Antalya Antiphellos Amphitheatre 06:30am",
    "url": "https://www.reddit.com/r/soccer/comments/1u5abv9/watch_party_in_turkey_antalya_antiphellos",
    "canonicalUrl": "https://www.reddit.com/r/soccer/comments/1u5abv9/watch_party_in_turkey_antalya_antiphellos/",
    "source": "Reddit",
    "sourceDetail": "r/soccer",
    "description": "Posted in r/soccer by u/WildBang • 2,623 points and 98 comments",
    "thumbnailRemoteUrl": "https://external-preview.redd.it/cmtiNWhweXo0NjdoMefIfaRzfP-GlxIbVeV1u7jQ3t1J8_X_9unb_AhqmJrs.png?width=140&height=140&crop=1:1,smart&format=jpg&auto=webp",
    "thumbnailLocalPath": null,
    "externalUrl": null,
    "archivedUrl": null,
    "postDate": "2026-06-14T03:35:39Z",
    "dateSaved": "2026-06-15T13:02:31Z",
    "matchId": "AUS-TUR-2026-06-13",
    "matchLabel": "🇦🇺 Australia vs 🇹🇷 Turkey",
    "stage": "Group stage",
    "group": "D",
    "teams": [
      "Australia",
      "Turkey"
    ],
    "teamCodes": [
      "AUS",
      "TUR"
    ],
    "scoreLabel": "🇦🇺 Australia 2–0 🇹🇷 Turkey",
    "goals": [
      {
        "team": "Australia",
        "player": "Nestory Irankunda",
        "minute": 27,
        "ownGoal": false,
        "penalty": false
      },
      {
        "team": "Australia",
        "player": "Connor Metcalfe",
        "minute": 75,
        "ownGoal": false,
        "penalty": false
      }
    ],
    "candidateMatches": [],
    "type": [],
    "tags": [],
    "pinnedTags": [],
    "suppressedTags": [],
    "importance": null,
    "note": "",
    "backup": "",
    "metadataConfidence": {
      "match": 1,
      "teams": 1,
      "stage": 1,
      "score": 1
    },
    "needsReview": false
  },
  {
    "id": "96e8cec09754",
    "title": "Qatar [1]-1 Switzerland - Boualem Khoukhi 90+4'",
    "url": "https://www.reddit.com/r/soccer/comments/1u527r0/qatar_11_switzerland_boualem_khoukhi_904",
    "canonicalUrl": "https://www.reddit.com/r/soccer/comments/1u527r0/qatar_11_switzerland_boualem_khoukhi_904/",
    "source": "Reddit",
    "sourceDetail": "r/soccer",
    "description": "Posted in r/soccer by u/977x • 4,694 points and 374 comments",
    "thumbnailRemoteUrl": "https://external-preview.redd.it/p46KU822VwCkQeiy5F2OvNI7x55fIlp0iqPPb00hhSs.jpeg?width=140&height=78&auto=webp",
    "thumbnailLocalPath": null,
    "externalUrl": null,
    "archivedUrl": null,
    "postDate": "2026-06-13T21:07:21Z",
    "dateSaved": "2026-06-15T13:03:15Z",
    "matchId": "QAT-SUI-2026-06-13",
    "matchLabel": "🇶🇦 Qatar vs 🇨🇭 Switzerland",
    "stage": "Group stage",
    "group": "B",
    "teams": [
      "Qatar",
      "Switzerland"
    ],
    "teamCodes": [
      "QAT",
      "SUI"
    ],
    "scoreLabel": "🇶🇦 Qatar 1–1 🇨🇭 Switzerland",
    "goals": [
      {
        "team": "Qatar",
        "player": "Boualem Khoukhi",
        "minute": 90,
        "ownGoal": false,
        "penalty": false
      },
      {
        "team": "Switzerland",
        "player": "Breel Embolo",
        "minute": 17,
        "ownGoal": false,
        "penalty": true
      }
    ],
    "candidateMatches": [],
    "type": [],
    "tags": [
      "Goal",
      "Highlights"
    ],
    "pinnedTags": [],
    "suppressedTags": [],
    "importance": null,
    "note": "",
    "backup": "",
    "metadataConfidence": {
      "match": 1,
      "teams": 1,
      "stage": 1,
      "score": 1
    },
    "needsReview": false
  },
  {
    "id": "c9b4a57b4808",
    "title": "Alisson save against Morocco 90+9'",
    "url": "https://www.reddit.com/r/soccer/comments/1u564bp/alisson_save_against_morocco_909",
    "canonicalUrl": "https://www.reddit.com/r/soccer/comments/1u564bp/alisson_save_against_morocco_909/",
    "source": "Reddit",
    "sourceDetail": "r/soccer",
    "description": "Posted in r/soccer by u/Gentle_lips • 2,359 points and 233 comments",
    "thumbnailRemoteUrl": "https://external-preview.redd.it/yceN26rgXq7CWsPb7DhmD7pRkxh9ADYh4t2D50oHtkQ.jpeg?width=140&height=69&auto=webp",
    "thumbnailLocalPath": null,
    "externalUrl": null,
    "archivedUrl": null,
    "postDate": "2026-06-14T00:05:28Z",
    "dateSaved": "2026-06-15T13:03:55Z",
    "matchId": "BRA-MAR-2026-06-13",
    "matchLabel": "🇧🇷 Brazil vs 🇲🇦 Morocco",
    "stage": "Group stage",
    "group": "C",
    "teams": [
      "Brazil",
      "Morocco"
    ],
    "teamCodes": [
      "BRA",
      "MAR"
    ],
    "scoreLabel": "🇧🇷 Brazil 1–1 🇲🇦 Morocco",
    "goals": [
      {
        "team": "Brazil",
        "player": "Vinícius Júnior",
        "minute": 32,
        "ownGoal": false,
        "penalty": false
      },
      {
        "team": "Morocco",
        "player": "Ismael Saibari",
        "minute": 21,
        "ownGoal": false,
        "penalty": false
      }
    ],
    "candidateMatches": [],
    "type": [],
    "tags": [
      "Saves",
      "Highlights"
    ],
    "pinnedTags": [],
    "suppressedTags": [],
    "importance": null,
    "note": "",
    "backup": "",
    "metadataConfidence": {
      "match": 1,
      "teams": 1,
      "stage": 1,
      "score": 1
    },
    "needsReview": false
  },
  {
    "id": "76ddda42c5b4",
    "title": "Haiti 0 - [1] Scotland - J. McGinn 28'",
    "url": "https://www.reddit.com/r/soccer/comments/1u57u6u/haiti_0_1_scotland_j_mcginn_28",
    "canonicalUrl": "https://www.reddit.com/r/soccer/comments/1u57u6u/haiti_0_1_scotland_j_mcginn_28/",
    "source": "Reddit",
    "sourceDetail": "r/soccer",
    "description": "Posted in r/soccer by u/gbogaz • 1,689 points and 123 comments",
    "thumbnailRemoteUrl": "https://www.redditstatic.com/new-icon.png",
    "thumbnailLocalPath": "assets/thumbs/76ddda42c5b4.png",
    "externalUrl": null,
    "archivedUrl": null,
    "postDate": "2026-06-14T01:30:35Z",
    "dateSaved": "2026-06-15T13:04:33Z",
    "matchId": "HAI-SCO-2026-06-13",
    "matchLabel": "🇭🇹 Haiti vs 🏴󠁧󠁢󠁳󠁣󠁴󠁿 Scotland",
    "stage": "Group stage",
    "group": "C",
    "teams": [
      "Haiti",
      "Scotland"
    ],
    "teamCodes": [
      "HAI",
      "SCO"
    ],
    "scoreLabel": "🇭🇹 Haiti 0–1 🏴󠁧󠁢󠁳󠁣󠁴󠁿 Scotland",
    "goals": [
      {
        "team": "Scotland",
        "player": "John McGinn",
        "minute": 28,
        "ownGoal": false,
        "penalty": false
      }
    ],
    "candidateMatches": [],
    "type": [],
    "tags": [
      "Goal",
      "Highlights"
    ],
    "pinnedTags": [],
    "suppressedTags": [],
    "importance": null,
    "note": "",
    "backup": "",
    "metadataConfidence": {
      "match": 1,
      "teams": 1,
      "stage": 1,
      "score": 1
    },
    "needsReview": false
  },
  {
    "id": "cfa2cdfa055a",
    "title": "The Scottish have taken over Boston harbour, full pints at 11 AM",
    "url": "https://www.reddit.com/r/soccer/comments/1u518rg/the_scottish_have_taken_over_boston_harbour_full",
    "canonicalUrl": "https://www.reddit.com/r/soccer/comments/1u518rg/the_scottish_have_taken_over_boston_harbour_full/",
    "source": "Reddit",
    "sourceDetail": "r/soccer",
    "description": "Source: @calbell0 (Callum Bell) on X",
    "thumbnailRemoteUrl": "https://external-preview.redd.it/c3M1dW84YmkwNDdoMW26NZymjKUGhQS9LZR3RlyUmxXbAia0vC09K1ILTUM0.png?width=140&height=140&crop=1:1,smart&format=jpg&auto=webp",
    "thumbnailLocalPath": null,
    "externalUrl": null,
    "archivedUrl": null,
    "postDate": "2026-06-13T20:26:57Z",
    "dateSaved": "2026-06-15T13:05:17Z",
    "matchId": "HAI-SCO-2026-06-13",
    "matchLabel": "🇭🇹 Haiti vs 🏴󠁧󠁢󠁳󠁣󠁴󠁿 Scotland",
    "stage": "Group stage",
    "group": "C",
    "teams": [
      "Haiti",
      "Scotland"
    ],
    "teamCodes": [
      "HAI",
      "SCO"
    ],
    "scoreLabel": "🇭🇹 Haiti 0–1 🏴󠁧󠁢󠁳󠁣󠁴󠁿 Scotland",
    "goals": [
      {
        "team": "Scotland",
        "player": "John McGinn",
        "minute": 28,
        "ownGoal": false,
        "penalty": false
      }
    ],
    "candidateMatches": [],
    "type": [],
    "tags": [],
    "pinnedTags": [],
    "suppressedTags": [],
    "importance": null,
    "note": "",
    "backup": "",
    "metadataConfidence": {
      "match": 1,
      "teams": 1,
      "stage": 1,
      "score": 1
    },
    "needsReview": false
  },
  {
    "id": "1f9e361f8117",
    "title": "Brazil fans take over Times Square in New York City.",
    "url": "https://www.reddit.com/r/soccer/comments/1u5093t/brazil_fans_take_over_times_square_in_new_york",
    "canonicalUrl": "https://www.reddit.com/r/soccer/comments/1u5093t/brazil_fans_take_over_times_square_in_new_york/",
    "source": "Reddit",
    "sourceDetail": "r/soccer",
    "description": "Posted in r/soccer by u/InspectorExact3836 • 2,550 points and 144 comments",
    "thumbnailRemoteUrl": "https://external-preview.redd.it/bTYwbWprdm5zMzdoMfaKq3KDautHZFCin641HmcEXTnT2BKTrRUrgNSXcAa3.png?width=140&height=140&crop=1:1,smart&format=jpg&auto=webp",
    "thumbnailLocalPath": null,
    "externalUrl": null,
    "archivedUrl": null,
    "postDate": "2026-06-13T19:45:58Z",
    "dateSaved": "2026-06-15T13:05:58Z",
    "matchId": "BRA-MAR-2026-06-13",
    "matchLabel": "🇧🇷 Brazil vs 🇲🇦 Morocco",
    "stage": "Group stage",
    "group": "C",
    "teams": [
      "Brazil",
      "Morocco"
    ],
    "teamCodes": [
      "BRA",
      "MAR"
    ],
    "scoreLabel": "🇧🇷 Brazil 1–1 🇲🇦 Morocco",
    "goals": [
      {
        "team": "Brazil",
        "player": "Vinícius Júnior",
        "minute": 32,
        "ownGoal": false,
        "penalty": false
      },
      {
        "team": "Morocco",
        "player": "Ismael Saibari",
        "minute": 21,
        "ownGoal": false,
        "penalty": false
      }
    ],
    "candidateMatches": [],
    "type": [],
    "tags": [
      "Vibes"
    ],
    "pinnedTags": [],
    "suppressedTags": [],
    "importance": null,
    "note": "",
    "backup": "",
    "metadataConfidence": {
      "match": 1,
      "teams": 1,
      "stage": 1,
      "score": 1
    },
    "needsReview": false
  },
  {
    "id": "6c1b3cb9a5af",
    "title": "An attempted pitch invader at the U.S.-Paraguay match was not able to make it even a step onto the pitch before being tackled by security",
    "url": "https://www.reddit.com/r/soccer/comments/1u4viip/an_attempted_pitch_invader_at_the_usparaguay",
    "canonicalUrl": "https://www.reddit.com/r/soccer/comments/1u4viip/an_attempted_pitch_invader_at_the_usparaguay/",
    "source": "Reddit",
    "sourceDetail": "r/soccer",
    "description": "Posted in r/soccer by u/Goosedukee • 3,913 points and 241 comments",
    "thumbnailRemoteUrl": "https://external-preview.redd.it/YXQxcmJ6end1MjdoMQyjuZqoyO85v4XfZxbDb-3Wy9uwzneiDb_S4zcGZarg.png?width=140&height=78&format=jpg&auto=webp",
    "thumbnailLocalPath": null,
    "externalUrl": null,
    "archivedUrl": "https://web.archive.org/web/20260614010901/https://www.reddit.com/r/soccer/comments/1u4viip/an_attempted_pitch_invader_at_the_usparaguay/",
    "postDate": "2026-06-13T16:35:53Z",
    "dateSaved": "2026-06-15T13:06:01Z",
    "matchId": "USA-PAR-2026-06-12",
    "matchLabel": "🇺🇸 USA vs 🇵🇾 Paraguay",
    "stage": "Group stage",
    "group": "D",
    "teams": [
      "USA",
      "Paraguay"
    ],
    "teamCodes": [
      "USA",
      "PAR"
    ],
    "scoreLabel": "🇺🇸 USA 4–1 🇵🇾 Paraguay",
    "goals": [
      {
        "team": "USA",
        "player": "Damian Bobadilla",
        "minute": 7,
        "ownGoal": true,
        "penalty": false
      },
      {
        "team": "USA",
        "player": "Folarin Balogun",
        "minute": 31,
        "ownGoal": false,
        "penalty": false
      },
      {
        "team": "USA",
        "player": "Folarin Balogun",
        "minute": 45,
        "ownGoal": false,
        "penalty": false
      },
      {
        "team": "USA",
        "player": "Giovanni Reyna",
        "minute": 90,
        "ownGoal": false,
        "penalty": false
      },
      {
        "team": "Paraguay",
        "player": "Mauricio",
        "minute": 73,
        "ownGoal": false,
        "penalty": false
      }
    ],
    "candidateMatches": [],
    "type": [],
    "tags": [],
    "pinnedTags": [],
    "suppressedTags": [],
    "importance": null,
    "note": "",
    "backup": "",
    "metadataConfidence": {
      "match": 1,
      "teams": 1,
      "stage": 1,
      "score": 1
    },
    "needsReview": false
  },
  {
    "id": "519276092c88",
    "title": "Qatar 0 - [1] Switzerland - Breel Embolo 17'",
    "url": "https://www.reddit.com/r/soccer/comments/1u4znvm/qatar_0_1_switzerland_breel_embolo_17",
    "canonicalUrl": "https://www.reddit.com/r/soccer/comments/1u4znvm/qatar_0_1_switzerland_breel_embolo_17/",
    "source": "Reddit",
    "sourceDetail": "r/soccer",
    "description": "Posted in r/soccer by u/Ihattaren • 1,033 points and 239 comments",
    "thumbnailRemoteUrl": "https://www.redditstatic.com/new-icon.png",
    "thumbnailLocalPath": "assets/thumbs/519276092c88.png",
    "externalUrl": null,
    "archivedUrl": null,
    "postDate": "2026-06-13T19:21:21Z",
    "dateSaved": "2026-06-15T13:06:39Z",
    "matchId": "QAT-SUI-2026-06-13",
    "matchLabel": "🇶🇦 Qatar vs 🇨🇭 Switzerland",
    "stage": "Group stage",
    "group": "B",
    "teams": [
      "Qatar",
      "Switzerland"
    ],
    "teamCodes": [
      "QAT",
      "SUI"
    ],
    "scoreLabel": "🇶🇦 Qatar 1–1 🇨🇭 Switzerland",
    "goals": [
      {
        "team": "Qatar",
        "player": "Boualem Khoukhi",
        "minute": 90,
        "ownGoal": false,
        "penalty": false
      },
      {
        "team": "Switzerland",
        "player": "Breel Embolo",
        "minute": 17,
        "ownGoal": false,
        "penalty": true
      }
    ],
    "candidateMatches": [],
    "type": [],
    "tags": [
      "Goal",
      "Highlights"
    ],
    "pinnedTags": [],
    "suppressedTags": [],
    "importance": null,
    "note": "",
    "backup": "",
    "metadataConfidence": {
      "match": 1,
      "teams": 1,
      "stage": 1,
      "score": 1
    },
    "needsReview": false
  },
  {
    "id": "13fb0a087bf0",
    "title": "FIFA shares onside animation graphic from Switzerland penalty award",
    "url": "https://www.reddit.com/r/soccer/comments/1u56567/fifa_shares_onside_animation_graphic_from",
    "canonicalUrl": "https://www.reddit.com/r/soccer/comments/1u56567/fifa_shares_onside_animation_graphic_from/",
    "source": "Reddit",
    "sourceDetail": "r/soccer",
    "description": "Posted in r/soccer by u/wybird • 604 points and 139 comments",
    "thumbnailRemoteUrl": "https://preview.redd.it/s7errvbp357h1.jpg?width=140&height=78&auto=webp",
    "thumbnailLocalPath": null,
    "externalUrl": null,
    "archivedUrl": null,
    "postDate": "2026-06-14T00:06:36Z",
    "dateSaved": "2026-06-15T13:07:17Z",
    "matchId": "QAT-SUI-2026-06-13",
    "matchLabel": "🇶🇦 Qatar vs 🇨🇭 Switzerland",
    "stage": "Group stage",
    "group": "B",
    "teams": [
      "Qatar",
      "Switzerland"
    ],
    "teamCodes": [
      "QAT",
      "SUI"
    ],
    "scoreLabel": "🇶🇦 Qatar 1–1 🇨🇭 Switzerland",
    "goals": [
      {
        "team": "Qatar",
        "player": "Boualem Khoukhi",
        "minute": 90,
        "ownGoal": false,
        "penalty": false
      },
      {
        "team": "Switzerland",
        "player": "Breel Embolo",
        "minute": 17,
        "ownGoal": false,
        "penalty": true
      }
    ],
    "candidateMatches": [],
    "type": [],
    "tags": [],
    "pinnedTags": [],
    "suppressedTags": [],
    "importance": null,
    "note": "",
    "backup": "",
    "metadataConfidence": {
      "match": 1,
      "teams": 1,
      "stage": 1,
      "score": 1
    },
    "needsReview": false
  }
]
